podsearch_test2/__init__.py
podsearch_test2-0.1.0.dist-info/WHEEL
podsearch_test2-0.1.0.dist-info/METADATA
podsearch_test2-0.1.0.dist-info/RECORD
