Metadata-Version: 2.1
Name: podsearch_test2
Version: 0.1.0
Summary: Let's find some podcasts!
Author: zhihao
Author-email: m@antonz.org
Classifier: License :: OSI Approved :: MIT License
